ei/__about__.py
ei/__init__.py
ei/main.py
ei/core/__init__.py
ei/core/cli.py
ei/core/concurrency.py
ei/core/defaults.py
ei/core/exceptions.py
ei/core/fields.py
ei/core/server.py
ei/core/service.py
ei/core/session.py
ei/core/table.py
ei/core/utils.py
ei/services/__init__.py
ei/services/aws/__init__.py
ei/services/aws/ec2.py
ei/services/aws/elasticache.py
ei/services/aws/elb.py
ei/services/aws/rds.py
ei/services/aws/s3.py
ei/views/__init__.py
ei/views/cli/__init__.py
ei/views/cli/ec2.py
ei/views/cli/elasticache.py
ei/views/cli/elb.py
ei/views/cli/rds.py
ei/views/cli/s3.py
ei_cli-0.16.0.dist-info/METADATA
ei_cli-0.16.0.dist-info/WHEEL
ei_cli-0.16.0.dist-info/entry_points.txt
ei_cli-0.16.0.dist-info/RECORD
