Metadata-Version: 2.4
Name: ei-cli
Version: 0.16.0
Summary: aws cli for human
Project-URL: Documentation, https://github.com/unknown/ei#readme
Project-URL: Issues, https://github.com/unknown/ei/issues
Project-URL: Source, https://github.com/unknown/ei
Author-email: Ashon <ashon8813@gmail.com>
License-Expression: MIT
Classifier: Development Status :: 4 - Beta
Classifier: Programming Language :: Python
Classifier: Programming Language :: Python :: 3.12
Classifier: Programming Language :: Python :: 3.13
Classifier: Programming Language :: Python :: Implementation :: CPython
Classifier: Programming Language :: Python :: Implementation :: PyPy
Requires-Python: >=3.13
Requires-Dist: boto3>=1.26.42
Requires-Dist: fastapi>=0.103.0
Requires-Dist: mypy-boto3-ec2>=1.26.34
Requires-Dist: mypy-boto3-elasticache>=1.26.11.post1
Requires-Dist: mypy-boto3-elbv2>=1.26.12
Requires-Dist: mypy-boto3-rds>=1.26.47
Requires-Dist: mypy-boto3-s3>=1.26.58
Requires-Dist: mypy-boto3>=1.26.42
Requires-Dist: pydantic-settings>=2.0.3
Requires-Dist: rich>=13.0.0
Requires-Dist: typer>=0.7.0
Requires-Dist: uvicorn>=0.22.0; python_version < '3.8'
Requires-Dist: uvicorn>=0.23.2; python_version >= '3.8'
Requires-Dist: uvloop>=0.17.0
